daluke/__init__.py
daluke/collect_modelfile.py
daluke/data.py
daluke/model.py
daluke/serialize.py
daluke/analysis/__init__.py
daluke/analysis/dabert.py
daluke/analysis/last_epoch_acc.py
daluke/analysis/pretrain.py
daluke/api/__init__.py
daluke/api/automodels.py
daluke/api/cli.py
daluke/api/data.py
daluke/api/fetch_model.py
daluke/api/predict.py
daluke/ner/__init__.py
daluke/ner/data.py
daluke/ner/evaluation.py
daluke/ner/model.py
daluke/ner/run.py
daluke/ner/run_eval.py
daluke/ner/training.py
daluke/ner/analysis/__init__.py
daluke/ner/analysis/cross_validation.py
daluke/ner/analysis/hyper_optimization.py
daluke/ner/analysis/pred_corr.py
daluke/ner/analysis/pred_examples.py
daluke/ner/analysis/representation_examples.py
daluke/ner/analysis/representation_geometry.py
daluke/plot/__init__.py
daluke/plot/plot_calibration_ner.py
daluke/plot/plot_finetune_ner.py
daluke/plot/plot_pretraining.py
daluke/plot/plot_representations.py
daluke/pretrain/__init__.py
daluke/pretrain/model.py
daluke/pretrain/run.py
daluke/pretrain/train.py
daluke/pretrain/data/__init__.py
daluke/pretrain/data/build.py
daluke/pretrain/data/loader.py
daluke/pretrain/data/masking.py
daluke/pretrain/data/preprocess.py
daluke/pretrain/data/run.py
reproduction/__init__.py
reproduction/error_analyze.py
reproduction/danish_ner/__init__.py
reproduction/danish_ner/data.py
reproduction/danish_ner/evaluation.py
reproduction/danish_ner/main.py
reproduction/danish_ner/models.py
reproduction/danish_ner/results.py
tests/__init__.py
tests/test_data.py
tests/test_model.py
daluke-0.0.5.dist-info/LICENSE
daluke-0.0.5.dist-info/METADATA
daluke-0.0.5.dist-info/WHEEL
daluke-0.0.5.dist-info/entry_points.txt
daluke-0.0.5.dist-info/top_level.txt
daluke-0.0.5.dist-info/RECORD
